cafemap/__init__.py
cafemap/cafemap.py
cafemap/cv.py
cafemap/instance.py
cafemap/llc.py
cafemap/roc.py
cafemap/utils.py
cafemap-0.2.dist-info/DESCRIPTION.rst
cafemap-0.2.dist-info/METADATA
cafemap-0.2.dist-info/RECORD
cafemap-0.2.dist-info/WHEEL
cafemap-0.2.dist-info/metadata.json
cafemap-0.2.dist-info/top_level.txt
