Metadata-Version: 2.0
Name: cafemap
Version: 0.2
Summary: Python Implementation of CAFÉ-Map: Context Aware Feature Mapping for mining high dimensional biomedical data
Home-page: https://github.com/foxtrotmike/cafemap
Author: Dr. Fayyaz Minhas, Amina Asif, Muhammad Arif
Author-email: UNKNOWN
License: UNKNOWN
Platform: UNKNOWN
Classifier: Programming Language :: Python :: 3
Classifier: License :: OSI Approved :: MIT License
Classifier: Operating System :: OS Independent
